selenium_web_browser/__init__.py
selenium_web_browser/browser.py
selenium_web_browser-0.0.2.dist-info/LICENSE
selenium_web_browser-0.0.2.dist-info/METADATA
selenium_web_browser-0.0.2.dist-info/WHEEL
selenium_web_browser-0.0.2.dist-info/top_level.txt
selenium_web_browser-0.0.2.dist-info/RECORD
